pypsutil/__init__.py
pypsutil/_bsd.py
pypsutil/_cache.py
pypsutil/_detect.py
pypsutil/_errors.py
pypsutil/_ffi.py
pypsutil/_ifaddrs.py
pypsutil/_process.py
pypsutil/_psfreebsd.py
pypsutil/_pslinux.py
pypsutil/_psmacosx.py
pypsutil/_psnetbsd.py
pypsutil/_psopenbsd.py
pypsutil/_psposix.py
pypsutil/_system.py
pypsutil/_util.py
pypsutil/py.typed
pypsutil/compat/__init__.py
pypsutil/compat/psutil.py
pypsutil-0.2.0.dist-info/LICENSE
pypsutil-0.2.0.dist-info/METADATA
pypsutil-0.2.0.dist-info/WHEEL
pypsutil-0.2.0.dist-info/top_level.txt
pypsutil-0.2.0.dist-info/RECORD
