Metadata-Version: 2.1
Name: pypsutil
Version: 0.2.0
Summary: A partial reimplementation of psutil in pure Python using ctypes.
Home-page: https://github.com/cptpcrd/pypsutil
License: MIT
Project-URL: Documentation, https://pypsutil.readthedocs.io/en/latest
Keywords: psutil
Platform: UNKNOWN
Classifier: License :: OSI Approved :: MIT License
Classifier: Programming Language :: Python :: 3.6
Classifier: Programming Language :: Python :: 3.7
Classifier: Programming Language :: Python :: 3.8
Classifier: Programming Language :: Python :: 3.9
Classifier: Programming Language :: Python :: 3.10
Classifier: Operating System :: POSIX :: Linux
Classifier: Operating System :: POSIX :: BSD :: OpenBSD
Classifier: Operating System :: POSIX :: BSD :: NetBSD
Classifier: Operating System :: POSIX :: BSD :: FreeBSD
Classifier: Operating System :: MacOS :: MacOS X
Requires-Python: >=3.6
License-File: LICENSE
Requires-Dist: dataclasses ; python_version < "3.7"
Requires-Dist: typing-extensions (>=3.10.0) ; python_version < "3.8"
